aoc/__init__.py
aoc/bit.py
aoc/hex.py
aoc/linked_list.py
aoc/point.py
aoc/rect.py
aoc/tree.py
aoc/utils.py
aoc_lib-1.1.7.dist-info/LICENSE
aoc_lib-1.1.7.dist-info/METADATA
aoc_lib-1.1.7.dist-info/WHEEL
aoc_lib-1.1.7.dist-info/top_level.txt
aoc_lib-1.1.7.dist-info/RECORD
