Metadata-Version: 2.1
Name: aoc-lib
Version: 1.1.7
Summary: Some helper functions for advent of code puzzles
Home-page: https://github.com/spossner/aoc
Author: Seppo
Author-email: aoc@possner.de
Classifier: Programming Language :: Python :: 3
Classifier: License :: OSI Approved :: MIT License
Classifier: Operating System :: OS Independent
Requires-Python: >=3.7
License-File: LICENSE
